postpygraphql/__init__.py
postpygraphql/core.py
postpygraphql/extractors.py
postpygraphql-0.0.5.dist-info/LICENSE.md
postpygraphql-0.0.5.dist-info/METADATA
postpygraphql-0.0.5.dist-info/WHEEL
postpygraphql-0.0.5.dist-info/top_level.txt
postpygraphql-0.0.5.dist-info/RECORD
