Metadata-Version: 2.1
Name: postpygraphql
Version: 0.0.5
Summary: A library to use postman collection V2.1 in python.
Home-page: https://github.com/dtregubov/postpygraphql
Author: Dmitriy Tregubov
Author-email: hedin358@mail.ru
License: UNKNOWN
Download-URL: https://codeload.github.com/dtregubov/postpygraphql/zip/master
Keywords: postman,python,graphql,rest,api,testing,automation
Platform: UNKNOWN
Classifier: Programming Language :: Python :: 3
Classifier: License :: OSI Approved :: GNU General Public License v3 (GPLv3)
Classifier: Operating System :: OS Independent
Requires-Python: >=3.6
License-File: LICENSE.md
Requires-Dist: requests
Requires-Dist: python-magic
